LICENSE
MANIFEST.in
README.md
setup.cfg
setup.py
anonympy/__init__.py
anonympy.egg-info/PKG-INFO
anonympy.egg-info/SOURCES.txt
anonympy.egg-info/dependency_links.txt
anonympy.egg-info/not-zip-safe
anonympy.egg-info/requires.txt
anonympy.egg-info/top_level.txt
anonympy/__pycache__/__init__.cpython-310.pyc
anonympy/__pycache__/__init__.cpython-39.pyc
anonympy/images/__init__.py
anonympy/images/cascade.xml
anonympy/images/core_images.py
anonympy/images/utils_images.py
anonympy/images/__pycache__/__init__.cpython-310.pyc
anonympy/images/__pycache__/__init__.cpython-39.pyc
anonympy/images/__pycache__/core.cpython-39.pyc
anonympy/images/__pycache__/core_images.cpython-310.pyc
anonympy/images/__pycache__/utils.cpython-310.pyc
anonympy/images/__pycache__/utils.cpython-39.pyc
anonympy/images/__pycache__/utils_images.cpython-310.pyc
anonympy/pandas/__init__.py
anonympy/pandas/core_pandas.py
anonympy/pandas/utils_pandas.py
anonympy/pandas/__pycache__/__init__.cpython-310.pyc
anonympy/pandas/__pycache__/__init__.cpython-39.pyc
anonympy/pandas/__pycache__/core.cpython-39.pyc
anonympy/pandas/__pycache__/core_pandas.cpython-310.pyc
anonympy/pandas/__pycache__/utils.cpython-39.pyc
anonympy/pandas/__pycache__/utils_pandas.cpython-310.pyc
anonympy/pdf/__init__.py
anonympy/pdf/core_pdf.py
anonympy/pdf/utils_pdf.py
anonympy/pdf/__pycache__/__init__.cpython-310.pyc
anonympy/pdf/__pycache__/core_pdf.cpython-310.pyc
anonympy/pdf/__pycache__/utils_pdf.cpython-310.pyc
anonympy/pdf/files/easyOCR_transformers.py
anonympy/pdf/files/pytesseract_transformers.py
anonympy/pdf/files/spacy_pdf_ocr.py
anonympy/sound/__init__.py
anonympy/sound/__pycache__/__init__.cpython-310.pyc
anonympy/sound/__pycache__/__init__.cpython-39.pyc
anonympy/tests/images/test_core_images.py
anonympy/tests/images/test_utils_images.py
anonympy/tests/images/__pycache__/test_core.cpython-310-pytest-7.0.1.pyc
anonympy/tests/images/__pycache__/test_core.cpython-39-pytest-6.2.4.pyc
anonympy/tests/images/__pycache__/test_core_images.cpython-310-pytest-7.0.1.pyc
anonympy/tests/images/__pycache__/test_core_images.cpython-310-pytest-7.1.1.pyc
anonympy/tests/images/__pycache__/test_utils.cpython-39-pytest-6.2.4.pyc
