Metadata-Version: 2.1
Name: anonympy
Version: 0.3.7
Summary: A Data Anonymization package for tabular, image and PDF data
Home-page: https://github.com/ArtLabss/open-data-anonimizer
Author: ArtLabs
Author-email: art@artlabs.tech
License: BSD license
Keywords: anonympy
Platform: UNKNOWN
Classifier: Development Status :: 3 - Alpha
Classifier: Intended Audience :: Developers
Classifier: License :: OSI Approved :: BSD License
Classifier: Natural Language :: English
Classifier: Programming Language :: Python :: 3.7
Classifier: Programming Language :: Python :: 3.8
Classifier: Programming Language :: Python :: 3.9
Classifier: Programming Language :: Python :: 3.10
Classifier: Operating System :: OS Independent
Classifier: Topic :: Scientific/Engineering :: Artificial Intelligence
Classifier: Topic :: Security :: Cryptography
Requires-Python: >=3.6*
License-File: LICENSE
